docopt_c/__init__.py
docopt_c/__main__.py
docopt_c/docopt.py
docopt_c/docopt_c.py
docopt_c-0.0.3.data/data/lib/python3.9/site-packages/docopt_c/_data/docopt.c
docopt_c-0.0.3.data/data/lib/python3.9/site-packages/docopt_c/_data/example.c
docopt_c-0.0.3.data/data/lib/python3.9/site-packages/docopt_c/_data/example.docopt
docopt_c-0.0.3.data/data/lib/python3.9/site-packages/docopt_c/_data/log.h
docopt_c-0.0.3.data/data/lib/python3.9/site-packages/docopt_c/_data/template.c
docopt_c-0.0.3.data/data/lib/python3.9/site-packages/docopt_c/_data/template.h
docopt_c-0.0.3.data/data/lib/python3.9/site-packages/docopt_c/_data/test_docopt.c
docopt_c-0.0.3.dist-info/LICENSE-MIT
docopt_c-0.0.3.dist-info/METADATA
docopt_c-0.0.3.dist-info/WHEEL
docopt_c-0.0.3.dist-info/top_level.txt
docopt_c-0.0.3.dist-info/RECORD
